decitobin/__init__.py
decitobin-2025.6.dist-info/licenses/LICENSE
decitobin-2025.6.dist-info/METADATA
decitobin-2025.6.dist-info/WHEEL
decitobin-2025.6.dist-info/top_level.txt
decitobin-2025.6.dist-info/RECORD
