Metadata-Version: 2.4
Name: decitobin
Version: 2025.6
Summary: A widget to convert decimal to binary, binary to decimal, ASCII to binary
Home-page: https://github.com/Thailam12/decimal-to-binary
Author: Your Name
Author-email: Thailam12 <thailam160317@outlook.com>
License-Expression: MIT
Project-URL: Homepage, https://github.com/Thailam12/decimal-to-binary
Project-URL: Issues, https://github.com/Thailam12/decimal-to-binary/issues
Classifier: Programming Language :: Python :: 3
Classifier: Operating System :: OS Independent
Requires-Python: >=3.10
License-File: LICENSE
Dynamic: author
Dynamic: home-page
Dynamic: license-file
Dynamic: requires-python
